.coveragerc
.flake8
CHANGELOG.md
LICENSE
MANIFEST.in
README.md
config.yaml
google-service-account-key-SAMPLE.json
mkdocs.yml
queries.yaml
requirements.txt
run.py
setup.cfg
setup.py
btl_cd_release_test.egg-info/PKG-INFO
btl_cd_release_test.egg-info/SOURCES.txt
btl_cd_release_test.egg-info/dependency_links.txt
btl_cd_release_test.egg-info/requires.txt
btl_cd_release_test.egg-info/top_level.txt
consensus_decentralization/__init__.py
consensus_decentralization/analyze.py
consensus_decentralization/collect_data.py
consensus_decentralization/helper.py
consensus_decentralization/map.py
consensus_decentralization/parse.py
consensus_decentralization/plot.py
consensus_decentralization/mappings/cardano_mapping.py
consensus_decentralization/mappings/default_mapping.py
consensus_decentralization/mappings/dummy_mapping.py
consensus_decentralization/mappings/ethereum_mapping.py
consensus_decentralization/mappings/tezos_mapping.py
consensus_decentralization/metrics/entropy.py
consensus_decentralization/metrics/gini.py
consensus_decentralization/metrics/herfindahl_hirschman_index.py
consensus_decentralization/metrics/nakamoto_coefficient.py
consensus_decentralization/parsers/default_parser.py
consensus_decentralization/parsers/dummy_parser.py
consensus_decentralization/parsers/ethereum_parser.py
docs/contribute.md
docs/data.md
docs/index.md
docs/mappings.md
docs/metrics.md
docs/parsers.md
docs/setup.md
mapping_information/README.md
mapping_information/get_cardano_info.py
mapping_information/legal_links.json
mapping_information/special_addresses.json
mapping_information/addresses/bitcoin.json
mapping_information/addresses/bitcoin_cash.json
mapping_information/addresses/ethereum.json
mapping_information/addresses/litecoin.json
mapping_information/addresses/test.json
mapping_information/addresses/tezos.json
mapping_information/cardano_preprocessing/cardano_clusters.json
mapping_information/cardano_preprocessing/cardano_conflicts.json
mapping_information/cardano_preprocessing/cardano_identifiers.json
mapping_information/cardano_preprocessing/cardano_pool_data.json
mapping_information/clusters/cardano.json
mapping_information/clusters/test.json
mapping_information/identifiers/bitcoin.json
