Metadata-Version: 2.1
Name: btl-cd-release-test
Version: 0.0.2
Summary: Blockchain-Technology-Lab Consensus Decentralization Tool
Home-page: https://github.com/Blockchain-Technology-Lab/consensus-decentralization/
Author: fnmokhtar
Author-email: fnmokhtar@outlook.fr
Keywords: Blockchain Technology Lab, Consensus, Decentralization
Classifier: Development Status :: 4 - Beta
Classifier: Framework :: Pytest
Classifier: Intended Audience :: Information Technology
Classifier: Operating System :: POSIX
Classifier: Programming Language :: Python :: 3.8
Requires-Python: >=3.8
License-File: LICENSE
